Metadata-Version: 2.1
Name: random-quote-generator-rdobmk
Version: 0.1.0
Summary: 
Author: rdobmk
Requires-Python: >=3.10,<4.0
Classifier: Programming Language :: Python :: 3
Classifier: Programming Language :: Python :: 3.10
Classifier: Programming Language :: Python :: 3.11
Requires-Dist: readthedocs-sphinx-search (>=0.3.1,<0.4.0)
Requires-Dist: sphinx (>=7.2.5,<8.0.0)
Requires-Dist: sphinx-rtd-theme (>=1.3.0,<2.0.0)
